Metadata-Version: 1.0
Name: tri-distributions
Version: 0.1
Summary: Gaussian distributions
Home-page: UNKNOWN
Author: Andrew Doan
Author-email: tri.sidoan@gmail.com
License: UNKNOWN
Platform: UNKNOWN
